pycollector-0.4.6-py3.9-nspkg.pth
pycollector/backend.py
pycollector/dataset.py
pycollector/globals.py
pycollector/label.py
pycollector/project.py
pycollector/user.py
pycollector/util.py
pycollector/version.py
pycollector/video.py
pycollector-0.4.6.dist-info/LICENSE
pycollector-0.4.6.dist-info/METADATA
pycollector-0.4.6.dist-info/WHEEL
pycollector-0.4.6.dist-info/namespace_packages.txt
pycollector-0.4.6.dist-info/top_level.txt
pycollector-0.4.6.dist-info/RECORD
