Metadata-Version: 2.1
Name: pycollector
Version: 0.4.6
Summary: Visym Collector
Home-page: https://github.com/visym/collector
Author: Visym Labs
Author-email: info@visym.com
License: UNKNOWN
Download-URL: https://github.com/visym/collector/archive/0.4.6.tar.gz
Keywords: computer vision machine learning ML CV privacy video image
Platform: UNKNOWN
Classifier: Programming Language :: Python :: 3
Classifier: Operating System :: OS Independent
Classifier: License :: OSI Approved :: GNU General Public License v3 (GPLv3)
License-File: LICENSE
Requires-Dist: vipy
Requires-Dist: heyvi
Requires-Dist: dask
Requires-Dist: distributed
Requires-Dist: boto3
Requires-Dist: pandas
Requires-Dist: torch
Requires-Dist: torchvision
Requires-Dist: pytorch-lightning
Requires-Dist: ujson
